wellsfargo/__init__.py
wellsfargo/admin.py
wellsfargo/apps.py
wellsfargo/handlers.py
wellsfargo/methods.py
wellsfargo/settings.py
wellsfargo/utils.py
wellsfargo/api/__init__.py
wellsfargo/api/apps.py
wellsfargo/api/exceptions.py
wellsfargo/api/serializers.py
wellsfargo/api/views.py
wellsfargo/connector/__init__.py
wellsfargo/connector/accounts.py
wellsfargo/connector/applications.py
wellsfargo/connector/client.py
wellsfargo/connector/health.py
wellsfargo/connector/prequal.py
wellsfargo/connector/transactions.py
wellsfargo/core/__init__.py
wellsfargo/core/constants.py
wellsfargo/core/exceptions.py
wellsfargo/core/fields.py
wellsfargo/core/signals.py
wellsfargo/core/structures.py
wellsfargo/dashboard/__init__.py
wellsfargo/dashboard/apps.py
wellsfargo/dashboard/forms.py
wellsfargo/dashboard/tables.py
wellsfargo/dashboard/views.py
wellsfargo/fixtures/wfrs-test.yaml
wellsfargo/fraud/__init__.py
wellsfargo/fraud/cybersource.py
wellsfargo/fraud/dummy.py
wellsfargo/locale/es/LC_MESSAGES/django.mo
wellsfargo/locale/es/LC_MESSAGES/django.po
wellsfargo/migrations/0001_squash_060.py
wellsfargo/migrations/0002_transfermetadata_credentials.py
wellsfargo/migrations/0003_auto_20170510_1633.py
wellsfargo/migrations/0004_auto_20170510_1712.py
wellsfargo/migrations/0005_financingplan_fine_print_superscript.py
wellsfargo/migrations/0006_financingplan_product_price_threshold.py
wellsfargo/migrations/0007_financingplan_advertising_enabled.py
wellsfargo/migrations/0008_fraudscreenresult.py
wellsfargo/migrations/0009_auto_20171005_1541.py
wellsfargo/migrations/0010_fraudscreenresult_reference.py
wellsfargo/migrations/0011_auto_20171204_1506.py
wellsfargo/migrations/0012_auto_20180102_1147.py
wellsfargo/migrations/0013_prequalificationrequest_prequalificationresponse.py
wellsfargo/migrations/0014_auto_20180222_1432.py
wellsfargo/migrations/0015_prequalificationresponse_reported_datetime.py
wellsfargo/migrations/0016_prequalificationresponse_customer_order.py
django_oscar_wfrs-5.2.0.dist-info/LICENSE
django_oscar_wfrs-5.2.0.dist-info/METADATA
django_oscar_wfrs-5.2.0.dist-info/WHEEL
django_oscar_wfrs-5.2.0.dist-info/top_level.txt
django_oscar_wfrs-5.2.0.dist-info/RECORD
